{
"meta":{"test_sets":[],"test_metrics":[],"learn_metrics":[{"best_value":"Min","name":"MultiClass"}],"launch_mode":"Train","parameters":"","iteration_count":50,"learn_sets":["learn"],"name":"experiment"},
"iterations":[
{"learn":[1.091490194],"iteration":0,"passed_time":0.04591746781,"remaining_time":2.249955923},
{"learn":[1.071204723],"iteration":1,"passed_time":0.04621499121,"remaining_time":1.109159789},
{"learn":[1.04931855],"iteration":2,"passed_time":0.04644055351,"remaining_time":0.7275686716},
{"learn":[1.044429847],"iteration":3,"passed_time":0.04656886511,"remaining_time":0.5355419488},
{"learn":[1.014988393],"iteration":4,"passed_time":0.04678494882,"remaining_time":0.4210645394},
{"learn":[0.9954096099],"iteration":5,"passed_time":0.04699250581,"remaining_time":0.3446117093},
{"learn":[0.9753501612],"iteration":6,"passed_time":0.04721271762,"remaining_time":0.2900209796},
{"learn":[0.952027322],"iteration":7,"passed_time":0.04743913158,"remaining_time":0.2490554408},
{"learn":[0.9324296079],"iteration":8,"passed_time":0.04764784083,"remaining_time":0.217062386},
{"learn":[0.9069020845],"iteration":9,"passed_time":0.04786848348,"remaining_time":0.1914739339},
{"learn":[0.8719205407],"iteration":10,"passed_time":0.04808799391,"remaining_time":0.1704937966},
{"learn":[0.8391784919],"iteration":11,"passed_time":0.0483222733,"remaining_time":0.1530205321},
{"learn":[0.8308717115],"iteration":12,"passed_time":0.04846577469,"remaining_time":0.137941051},
{"learn":[0.8066207753],"iteration":13,"passed_time":0.0486847641,"remaining_time":0.1251893934},
{"learn":[0.7877699549],"iteration":14,"passed_time":0.04890352305,"remaining_time":0.1141082205},
{"learn":[0.7734824174],"iteration":15,"passed_time":0.04912404547,"remaining_time":0.1043885966},
{"learn":[0.7414418269],"iteration":16,"passed_time":0.04935233311,"remaining_time":0.09580158779},
{"learn":[0.7228928238],"iteration":17,"passed_time":0.04957269521,"remaining_time":0.08812923592},
{"learn":[0.6911906282],"iteration":18,"passed_time":0.04980563196,"remaining_time":0.08126182057},
{"learn":[0.6651334187],"iteration":19,"passed_time":0.05004356852,"remaining_time":0.07506535279},
{"learn":[0.6516480644],"iteration":20,"passed_time":0.05025921137,"remaining_time":0.06940557761},
{"learn":[0.6326415006],"iteration":21,"passed_time":0.05049059508,"remaining_time":0.06426075738},
{"learn":[0.6219146385],"iteration":22,"passed_time":0.05070060688,"remaining_time":0.05951810373},
{"learn":[0.6124636819],"iteration":23,"passed_time":0.05092060828,"remaining_time":0.0551639923},
{"learn":[0.5926394697],"iteration":24,"passed_time":0.05112261438,"remaining_time":0.05112261438},
{"learn":[0.5806430129],"iteration":25,"passed_time":0.05133010124,"remaining_time":0.04738163191},
{"learn":[0.5668336849],"iteration":26,"passed_time":0.05154264801,"remaining_time":0.04390670016},
{"learn":[0.5582079383],"iteration":27,"passed_time":0.05175364174,"remaining_time":0.04066357565},
{"learn":[0.5453864769],"iteration":28,"passed_time":0.05195457574,"remaining_time":0.03762227899},
{"learn":[0.5257715035],"iteration":29,"passed_time":0.05212178362,"remaining_time":0.03474785574},
{"learn":[0.5161817286],"iteration":30,"passed_time":0.05230264827,"remaining_time":0.03205646184},
{"learn":[0.5109466347],"iteration":31,"passed_time":0.05247354337,"remaining_time":0.02951636814},
{"learn":[0.5036256247],"iteration":32,"passed_time":0.05265059053,"remaining_time":0.02712303149},
{"learn":[0.4944625817],"iteration":33,"passed_time":0.0528253432,"remaining_time":0.02485898503},
{"learn":[0.4770744952],"iteration":34,"passed_time":0.05299805186,"remaining_time":0.0227134508},
{"learn":[0.4599427422],"iteration":35,"passed_time":0.05317009922,"remaining_time":0.02067726081},
{"learn":[0.4473334421],"iteration":36,"passed_time":0.05334863931,"remaining_time":0.01874411651},
{"learn":[0.4366924547],"iteration":37,"passed_time":0.05351510573,"remaining_time":0.01689950707},
{"learn":[0.4299853979],"iteration":38,"passed_time":0.0536948582,"remaining_time":0.01514470359},
{"learn":[0.4172958421],"iteration":39,"passed_time":0.05386592363,"remaining_time":0.01346648091},
{"learn":[0.4058526036],"iteration":40,"passed_time":0.05404129752,"remaining_time":0.01186272385},
{"learn":[0.3936374174],"iteration":41,"passed_time":0.05422012818,"remaining_time":0.01032764346},
{"learn":[0.3831564341],"iteration":42,"passed_time":0.05439151424,"remaining_time":0.008854432551},
{"learn":[0.369948897],"iteration":43,"passed_time":0.05462760719,"remaining_time":0.007449219162},
{"learn":[0.3587878024],"iteration":44,"passed_time":0.05481275023,"remaining_time":0.006090305581},
{"learn":[0.350623557],"iteration":45,"passed_time":0.05499074926,"remaining_time":0.004781804284},
{"learn":[0.3437170494],"iteration":46,"passed_time":0.05517334731,"remaining_time":0.00352170302},
{"learn":[0.3353516964],"iteration":47,"passed_time":0.05534249899,"remaining_time":0.002305937458},
{"learn":[0.3299189238],"iteration":48,"passed_time":0.05551752219,"remaining_time":0.001133010657},
{"learn":[0.3273795914],"iteration":49,"passed_time":0.05562975226,"remaining_time":0}
]}